[{"name":"Casa nueva","email":"mdmdmdm@yopmail.com","address":"av siempre viva 23","phone":"8777483839","debt":"0","id":"dc3e3461-29c7-4486-ac1b-17d47f770ab5"},{"name":"dsjndmsaklasm","email":"ldkms@ypmail.com","phone":"l7564849450","address":"lkdmslakms","id":"81e82e36-36cb-42f2-aae9-2deb8bf699da"},{"email":"erasmo.dejesus@outlook.com","name":"Erasmo","phone":"5578023662","address":"CALLE SAUCES NO. 14","id":"a27a0938-713f-4ec6-a81b-7f6dbc6c2802"},{"name":"Erasmo","email":"erasmo.dejesus@outlook.com","phone":"5578023662","address":"CALLE SAUCES NO. 14","id":"07c79ae9-56ed-4c99-b934-f46ae185bf38"},{"name":"Erasmo","email":"erasmo.dejesus@outlook.com","phone":"5578023662","address":"CALLE SAUCES NO. 14","id":"677325e8-cc1d-4d03-92d9-4f628d5a1cbd"}]